Metadata-Version: 2.1
Name: yahoo-search-api-v11
Version: 1.0.4
Summary: Yahoo!広告 検索広告 API リファレンス / Yahoo! JAPAN Ads Search Ads API Reference
Home-page: UNKNOWN
Author: OpenAPI Generator community
Author-email: team@openapitools.org
License: UNKNOWN
Keywords: OpenAPI,OpenAPI-Generator,Yahoo!広告 検索広告 API リファレンス / Yahoo! JAPAN Ads Search Ads API Reference
Platform: UNKNOWN
Requires-Dist: urllib3 >=1.15
Requires-Dist: six >=1.10
Requires-Dist: certifi
Requires-Dist: python-dateutil
